MANIFEST.in
README.txt
setup.py
Products/__init__.py
Products.projectmanager.egg-info/PKG-INFO
Products.projectmanager.egg-info/SOURCES.txt
Products.projectmanager.egg-info/dependency_links.txt
Products.projectmanager.egg-info/entry_points.txt
Products.projectmanager.egg-info/namespace_packages.txt
Products.projectmanager.egg-info/not-zip-safe
Products.projectmanager.egg-info/requires.txt
Products.projectmanager.egg-info/top_level.txt
Products/projectmanager/__init__.py
Products/projectmanager/config.py
Products/projectmanager/configure.zcml
Products/projectmanager/generatedsubscribers.zcml
Products/projectmanager/gvgen.py
Products/projectmanager/profiles.zcml
Products/projectmanager/refresh.txt
Products/projectmanager/setuphandlers.py
Products/projectmanager/upgrades.py
Products/projectmanager/upgrades.zcml
Products/projectmanager/wfsubscribers.py
Products/projectmanager/browser/__init__.py
Products/projectmanager/browser/configure.zcml
Products/projectmanager/browser/diagramview.py
Products/projectmanager/browser/ganttview.pt
Products/projectmanager/browser/ganttview.py
Products/projectmanager/browser/humanressources.pt
Products/projectmanager/browser/pertview.pt
Products/projectmanager/browser/pertview.py
Products/projectmanager/browser/pm_gantt.css
Products/projectmanager/browser/projectganttview.py
Products/projectmanager/browser/projectpertview.pt
Products/projectmanager/browser/utils.py
Products/projectmanager/content/PM_Action.py
Products/projectmanager/content/PM_ProjectManager.py
Products/projectmanager/content/PM_Task.py
Products/projectmanager/content/__init__.py
Products/projectmanager/content/interfaces.py
Products/projectmanager/i18n/generated.pot
Products/projectmanager/i18n/projectmanager-plone-fr.po
Products/projectmanager/i18n/projectmanager-plone-manual-en.po
Products/projectmanager/i18n/projectmanager-plone-manual-fr.po
Products/projectmanager/locales/generate.sh
Products/projectmanager/locales/plone.pot
Products/projectmanager/locales/projectmanager.pot
Products/projectmanager/locales/update.sh
Products/projectmanager/locales/en/LC_MESSAGES/projectmanager.po
Products/projectmanager/locales/fr/LC_MESSAGES/projectmanager.po
Products/projectmanager/profiles/default/catalog.xml
Products/projectmanager/profiles/default/cssregistry.xml
Products/projectmanager/profiles/default/factorytool.xml
