Metadata-Version: 1.1
Name: Products.projectmanager
Version: 1.2.4
Summary: A product to manage projects for Plone. By Ecreall.
Home-page: https://svn.ecreall.com/public/Products.projectmanager
Author: Michael Launay and Vincent Fretin
Author-email: development@ecreall.com
License: GPL
Keywords: project manager plone
Platform: UNKNOWN
Classifier: Programming Language :: Python
Classifier: Topic :: Software Development :: User Interfaces
Classifier: Framework :: Plone
